__builtins__.pyi
_asyncio.pyi
_boot.pyi
_boot_fat.pyi
_onewire.pyi
_rp2.pyi
_thread.pyi
aioble/__init__.pyi
aioble/central.pyi
aioble/client.pyi
aioble/core.pyi
aioble/device.pyi
aioble/l2cap.pyi
aioble/peripheral.pyi
aioble/security.pyi
aioble/server.pyi
array.pyi
asyncio/__init__.pyi
asyncio/core.pyi
asyncio/event.pyi
asyncio/funcs.pyi
asyncio/lock.pyi
asyncio/stream.pyi
binascii.pyi
bluetooth.pyi
cbor2/__init__.pyi
cbor2/decoder.pyi
cbor2/encoder.pyi
cmath.pyi
cryptolib.pyi
deflate.pyi
dht.pyi
ds18x20.pyi
errno.pyi
espflash.pyi
framebuf.pyi
gc.pyi
hashlib.pyi
heapq.pyi
io.pyi
json.pyi
logging.pyi
lsm6dsox.pyi
machine.pyi
math.pyi
micropython.pyi
mip/__init__.pyi
neopixel.pyi
network.pyi
ntptime.pyi
onewire.pyi
os.pyi
platform.pyi
random.pyi
requests/__init__.pyi
rp2.pyi
select.pyi
senml/__init__.pyi
senml/senml_base.pyi
senml/senml_pack.pyi
senml/senml_record.pyi
senml/senml_unit.pyi
socket.pyi
ssl.pyi
struct.pyi
sys.pyi
time.pyi
uarray.pyi
uasyncio/__init__.pyi
uasyncio/core.pyi
uasyncio/event.pyi
uasyncio/funcs.pyi
uasyncio/lock.pyi
uasyncio/stream.pyi
uasyncio.pyi
ubinascii.pyi
ubluetooth.pyi
ucollections.pyi
ucryptolib.pyi
uctypes.pyi
uerrno.pyi
uhashlib.pyi
uheapq.pyi
uio.pyi
ujson.pyi
umachine.pyi
uos.pyi
uplatform.pyi
urandom.pyi
ure.pyi
urequests.pyi
uselect.pyi
usocket.pyi
ussl.pyi
ustruct.pyi
usys.pyi
utime.pyi
uwebsocket.pyi
webrepl.pyi
webrepl_setup.pyi
websocket.pyi
micropython_rp2_arduino_nano_rp2040_connect_stubs-1.22.1.post1.dist-info/LICENSE.md
micropython_rp2_arduino_nano_rp2040_connect_stubs-1.22.1.post1.dist-info/METADATA
micropython_rp2_arduino_nano_rp2040_connect_stubs-1.22.1.post1.dist-info/WHEEL
micropython_rp2_arduino_nano_rp2040_connect_stubs-1.22.1.post1.dist-info/RECORD
