Metadata-Version: 2.1
Name: micropython-rp2-arduino_nano_rp2040_connect-stubs
Version: 1.22.1.post1
Summary: MicroPython stubs
Home-page: https://github.com/josverl/micropython-stubs#micropython-stubs
License: MIT
Author: josverl
Author-email: josverl@users.noreply.github.com
Requires-Python: >=3.8,<4.0
Classifier: Development Status :: 5 - Production/Stable
Classifier: License :: OSI Approved :: MIT License
Classifier: Natural Language :: English
Classifier: Operating System :: OS Independent
Classifier: Programming Language :: Python
Classifier: Programming Language :: Python :: 3
Classifier: Programming Language :: Python :: 3.8
Classifier: Programming Language :: Python :: 3.9
Classifier: Programming Language :: Python :: 3.10
Classifier: Programming Language :: Python :: 3.11
Classifier: Programming Language :: Python :: 3 :: Only
Classifier: Programming Language :: Python :: Implementation :: MicroPython
Classifier: Topic :: Software Development :: Documentation
Classifier: Topic :: Software Development :: Embedded Systems
Classifier: Topic :: Software Development :: Testing
Classifier: Topic :: Text Editors :: Integrated Development Environments (IDE)
Classifier: Typing :: Stubs Only
Requires-Dist: micropython-stdlib-stubs (>=1.1.1)
Project-URL: Documentation, https://micropython-stubs.readthedocs.io/
Project-URL: Repository, https://github.com/josverl/micropython-stubs
